{
  "total_exercises": 48,
  "total_sets": 1858,
  "total_volume": 1575062.0,
  "top_exercises": [
    {
      "exercise": "Bench Press (Barbell)",
      "volume": 279750.0
    },
    {
      "exercise": "Squat (Barbell)",
      "volume": 180181.0
    },
    {
      "exercise": "Deadlift (Barbell)",
      "volume": 109135.0
    },
    {
      "exercise": "Incline Bench Press (Barbell)",
      "volume": 102640.0
    },
    {
      "exercise": "T Bar Row",
      "volume": 86890.0
    },
    {
      "exercise": "Lat Pulldown (Cable)",
      "volume": 79110.0
    },
    {
      "exercise": "Lying Leg Curl (Machine)",
      "volume": 73120.0
    },
    {
      "exercise": "Romanian Deadlift (Barbell)",
      "volume": 72090.0
    },
    {
      "exercise": "Hip Thrust (Barbell)",
      "volume": 65730.0
    },
    {
      "exercise": "Chest Press (Machine)",
      "volume": 49280.0
    }
  ],
  "category_distribution": [
    {
      "category": "Legs",
      "count": 621
    },
    {
      "category": "Chest",
      "count": 590
    },
    {
      "category": "Back",
      "count": 345
    },
    {
      "category": "Arms",
      "count": 128
    },
    {
      "category": "Shoulders",
      "count": 124
    },
    {
      "category": "Core",
      "count": 44
    },
    {
      "category": "Other",
      "count": 6
    }
  ],
  "category_volume": [
    {
      "category": "Legs",
      "volume": 657141.0
    },
    {
      "category": "Chest",
      "volume": 502760.0
    },
    {
      "category": "Back",
      "volume": 268560.0
    },
    {
      "category": "Shoulders",
      "volume": 68445.0
    },
    {
      "category": "Arms",
      "volume": 57706.0
    },
    {
      "category": "Core",
      "volume": 18950.0
    },
    {
      "category": "Other",
      "volume": 1500.0
    }
  ]
}